bitia/__init__.py
bitia/__main__.py
bitia/checksumdir.py
bitia/common.py
bitia/config.py
bitia/dsl.py
bitia/helper.py
bitia/logger.py
bitia/pipeline.py
bitia/session.py
bitia-0.2.3.dist-info/LICENSE
bitia-0.2.3.dist-info/METADATA
bitia-0.2.3.dist-info/WHEEL
bitia-0.2.3.dist-info/entry_points.txt
bitia-0.2.3.dist-info/RECORD
