Metadata-Version: 2.1
Name: bitia
Version: 0.2.3
Summary: BioInformatics Tool for Infrastructure Automation (BiTIA) CLI utility.
Author: Dilawar Singh
Author-email: dilawar@subcom.tech
Requires-Python: >=3.8,<4.0
Classifier: Programming Language :: Python :: 3
Classifier: Programming Language :: Python :: 3.8
Classifier: Programming Language :: Python :: 3.9
Classifier: Programming Language :: Python :: 3.10
Classifier: Programming Language :: Python :: 3.11
Requires-Dist: pyparsing (>=3.0.9,<4.0.0)
Requires-Dist: requests (>=2.28.1,<3.0.0)
Requires-Dist: rich (>=12.5.1,<13.0.0)
Requires-Dist: typer (>=0.6.1,<0.7.0)
Requires-Dist: validators (>=0.20.0,<0.21.0)
